setup.py
setup_pipinstall.py
ecscli/__init__.py
ecscli/alerts.py
ecscli/approval.py
ecscli/assetoptions.py
ecscli/authentication.py
ecscli/baseurl.py
ecscli/billing.py
ecscli/bucket.py
ecscli/capacity.py
ecscli/cashead.py
ecscli/catalog.py
ecscli/cluster.py
ecscli/common.py
ecscli/config.py
ecscli/consistencygroup.py
ecscli/customparser.py
ecscli/dashboard.py
ecscli/datafabric.py
ecscli/datastore.py
ecscli/ecscli.py
ecscli/ecscli_interpreter.py
ecscli/executionwindow.py
ecscli/exportgroup.py
ecscli/fabric.py
ecscli/failedzones.py
ecscli/fileshare.py
ecscli/host.py
ecscli/hostinitiators.py
ecscli/hostipinterfaces.py
ecscli/jira-17251.py
ecscli/key.py
ecscli/keypool.py
ecscli/keystore.py
ecscli/metering.py
ecscli/mgmtuserinfo.py
ecscli/monitoring.py
ecscli/network.py
ecscli/networksystem.py
ecscli/nfs.py
ecscli/nodes.py
ecscli/objectcos.py
ecscli/objectuser.py
ecscli/objectvpool.py
ecscli/order.py
ecscli/passwordgroup.py
ecscli/project.py
ecscli/protectionsystem.py
ecscli/quota.py
ecscli/reporting.py
ecscli/secretkeyuser.py
ecscli/setup.py
ecscli/snapshot.py
ecscli/storagepool.py
ecscli/storageport.py
ecscli/storageprovider.py
ecscli/storagesystem.py
ecscli/sysmanager.py
ecscli/sysmgrcontrolsvc.py
ecscli/tag.py
ecscli/tb.py
ecscli/tenant.py
ecscli/test.py
ecscli/test_31.py
ecscli/test_baseurl.py
ecscli/test_billing.py
ecscli/test_bucket.py
ecscli/test_cas.py
ecscli/test_common.py
ecscli/test_dashboard.py
ecscli/test_datafabric.py
ecscli/test_datastore.py
ecscli/test_failedzones.py
ecscli/test_keystore.py
ecscli/test_mgmtuserinfo.py
ecscli/test_namespace.py
ecscli/test_objectuser.py
ecscli/test_objectvpool.py
ecscli/test_passwordgroup.py
ecscli/test_secretkeyuser.py
ecscli/test_ssl.py
ecscli/test_system.py
ecscli/test_tenant.py
ecscli/test_transformation.py
ecscli/test_varray.py
ecscli/test_vdc.py
ecscli/test_vdckeystore.py
ecscli/test_virtualarray.py
ecscli/test_virtualdatacenterdata.py
ecscli/transformation.py
ecscli/truststore.py
ecscli/urihelper.py
ecscli.egg-info/PKG-INFO
ecscli.egg-info/SOURCES.txt
ecscli.egg-info/dependency_links.txt
ecscli.egg-info/entry_points.txt
ecscli.egg-info/requires.txt
ecscli.egg-info/top_level.txt