Metadata-Version: 1.0
Name: ecscli
Version: 3.1.23
Summary: an install of the ECS ecscli
Home-page: UNKNOWN
Author: joe conery
Author-email: joseph.conery@dell.com
License: UNKNOWN
Platform: UNKNOWN
